[{"isSaveData":true,"SaveDay":"2019. 01. 27 / 17\uC2DC 11\uBD84","_currItemDatasList":[],"_currEquipDatasList":[{"_Index":207,"_setUse":false},{"_Index":208,"_setUse":true}],"_currAidDatasList":[],"_useItemList":[],"_tileMapList":[{"_tileIndex":0,"_SafetyValue":0.0,"_isSafetyEff":false,"_isBlockade":false,"_isIssueIcon":false,"_isShop":false,"_isSpShop":false,"_isIssue":false,"_isCrime":false},{"_tileIndex":1,"_SafetyValue":0.0,"_isSafetyEff":false,"_isBlockade":false,"_isIssueIcon":false,"_isShop":true,"_isSpShop":false,"_isIssue":false,"_isCrime":false},{"_tileIndex":2,"_SafetyValue":0.0,"_isSafetyEff":false,"_isBlockade":false,"_isIssueIcon":false,"_isShop":false,"_isSpShop":false,"_isIssue":false,"_isCrime":false},{"_tileIndex":3,"_SafetyValue":0.0,"_isSafetyEff":false,"_isBlockade":false,"_isIssueIcon":false,"_isShop":false,"_isSpShop":false,"_isIssue":false,"_isCrime":false},{"_tileIndex":4,"_SafetyValue":0.0,"_isSafetyEff":false,"_isBlockade":false,"_isIssueIcon":false,"_isShop":false,"_isSpShop":false,"_isIssue":false,"_isCrime":false},{"_tileIndex":5,"_SafetyValue":0.0,"_isSafetyEff":false,"_isBlockade":false,"_isIssueIcon":false,"_isShop":false,"_isSpShop":false,"_isIssue":false,"_isCrime":false},{"_tileIndex":6,"_SafetyValue":0.0,"_isSafetyEff":false,"_isBlockade":false,"_isIssueIcon":false,"_isShop":false,"_isSpShop":false,"_isIssue":false,"_isCrime":false},{"_tileIndex":7,"_SafetyValue":0.0,"_isSafetyEff":false,"_isBlockade":false,"_isIssueIcon":false,"_isShop":false,"_isSpShop":true,"_isIssue":false,"_isCrime":false},{"_tileIndex":8,"_SafetyValue":0.0,"_isSafetyEff":false,"_isBlockade":false,"_isIssueIcon":false,"_isShop":false,"_isSpShop":false,"_isIssue":false,"_isCrime":false},{"_tileIndex":9,"_SafetyValue":0.0,"_isSafetyEff":false,"_isBlockade":false,"_isIssueIcon":false,"_isShop":false,"_isSpShop":false,"_isIssue":false,"_isCrime":false},{"_tileIndex":10,"_SafetyValue":0.0,"_isSafetyEff":false,"_isBlockade":false,"_isIssueIcon":false,"_isShop":false,"_isSpShop":false,"_isIssue":false,"_isCrime":false},{"_tileIndex":11,"_SafetyValue":0.0,"_isSafetyEff":false,"_isBlockade":false,"_isIssueIcon":false,"_isShop":false,"_isSpShop":false,"_isIssue":false,"_isCrime":false},{"_tileIndex":12,"_SafetyValue":0.0,"_isSafetyEff":false,"_isBlockade":false,"_isIssueIcon":false,"_isShop":false,"_isSpShop":false,"_isIssue":false,"_isCrime":false},{"_tileIndex":13,"_SafetyValue":0.0,"_isSafetyEff":false,"_isBlockade":false,"_isIssueIcon":false,"_isShop":false,"_isSpShop":false,"_isIssue":false,"_isCrime":false}],"_currEventID":7,"_clueTokenValue":0,"_isAlive":true,"_isTurn":false,"_daleyTurnCount":0,"_reasoningValue":3,"_currTile":1,"_tempCurrTile":0,"_currActPoint":99,"_currTrunPoint":1,"_currHP":20,"_MaxHP":20,"_atkPoint":2,"_WishIcon":{"_currTile":0,"_isAlive":false,"_isTurn":false},"_HamIcon":{"_currTile":0,"_isAlive":false,"_isTurn":false},"_HamSaveData":{"_currRoot":0,"_rootChangeValue":33.0,"_nextRootTile":0,"_currRootValue":0,"_currList":[],"_jeonMoveTileListA":[3,1,2,5],"_jeonMoveTileListB":[3,7,5],"_jeonMoveTileListC":[7,9,7,5]},"_JeonIcon":{"_currTile":0,"_isAlive":false,"_isTurn":false},"_JeonSaveData":{"_currRoot":0,"_rootChangeValue":50.0,"_nextRootTile":0,"_currRootValue":0,"_currList":[],"_jeonMoveTileListA":[5,1,0,2,6,10,11,12],"_jeonMoveTileListB":[12,10,7,8,4,0,3,1,5],"_jeonMoveTileListC":[7,0,2,0,4,9,11,13,5],"_jeonMoveTileListD":[11,8,4,0,1,2,8,11,12]},"_YoungIcon":{"_currTile":0,"_isAlive":false,"_isTurn":false},"_YoungSaveData":{"_nextRootTile":0,"_currRootValue":0,"_YoungMoveTileList":[7,8,9,10,11,12,13,12,11,10,9,8,7,6,5,4,6]}},{"isSaveData":true,"SaveDay":"2019. 01. 27 / 17\uC2DC 04\uBD84","_currItemDatasList":[],"_currEquipDatasList":[],"_currAidDatasList":[],"_useItemList":[],"_tileMapList":[{"_tileIndex":0,"_SafetyValue":0.0,"_isSafetyEff":false,"_isBlockade":false,"_isIssueIcon":false,"_isShop":false,"_isSpShop":false,"_isIssue":false,"_isCrime":false},{"_tileIndex":1,"_SafetyValue":0.0,"_isSafetyEff":false,"_isBlockade":false,"_isIssueIcon":false,"_isShop":true,"_isSpShop":false,"_isIssue":false,"_isCrime":false},{"_tileIndex":2,"_SafetyValue":0.0,"_isSafetyEff":false,"_isBlockade":false,"_isIssueIcon":false,"_isShop":false,"_isSpShop":false,"_isIssue":false,"_isCrime":false},{"_tileIndex":3,"_SafetyValue":0.0,"_isSafetyEff":false,"_isBlockade":false,"_isIssueIcon":false,"_isShop":false,"_isSpShop":false,"_isIssue":false,"_isCrime":false},{"_tileIndex":4,"_SafetyValue":0.0,"_isSafetyEff":false,"_isBlockade":false,"_isIssueIcon":false,"_isShop":false,"_isSpShop":false,"_isIssue":false,"_isCrime":false},{"_tileIndex":5,"_SafetyValue":0.0,"_isSafetyEff":false,"_isBlockade":false,"_isIssueIcon":false,"_isShop":false,"_isSpShop":false,"_isIssue":false,"_isCrime":false},{"_tileIndex":6,"_SafetyValue":0.0,"_isSafetyEff":false,"_isBlockade":false,"_isIssueIcon":false,"_isShop":false,"_isSpShop":false,"_isIssue":false,"_isCrime":false},{"_tileIndex":7,"_SafetyValue":0.0,"_isSafetyEff":false,"_isBlockade":false,"_isIssueIcon":false,"_isShop":false,"_isSpShop":true,"_isIssue":false,"_isCrime":false},{"_tileIndex":8,"_SafetyValue":0.0,"_isSafetyEff":false,"_isBlockade":false,"_isIssueIcon":false,"_isShop":false,"_isSpShop":false,"_isIssue":false,"_isCrime":false},{"_tileIndex":9,"_SafetyValue":0.0,"_isSafetyEff":false,"_isBlockade":false,"_isIssueIcon":false,"_isShop":false,"_isSpShop":false,"_isIssue":false,"_isCrime":false},{"_tileIndex":10,"_SafetyValue":0.0,"_isSafetyEff":false,"_isBlockade":false,"_isIssueIcon":false,"_isShop":false,"_isSpShop":false,"_isIssue":false,"_isCrime":false},{"_tileIndex":11,"_SafetyValue":0.0,"_isSafetyEff":false,"_isBlockade":false,"_isIssueIcon":false,"_isShop":false,"_isSpShop":false,"_isIssue":false,"_isCrime":false},{"_tileIndex":12,"_SafetyValue":0.0,"_isSafetyEff":false,"_isBlockade":false,"_isIssueIcon":false,"_isShop":false,"_isSpShop":false,"_isIssue":false,"_isCrime":false},{"_tileIndex":13,"_SafetyValue":0.0,"_isSafetyEff":false,"_isBlockade":false,"_isIssueIcon":false,"_isShop":false,"_isSpShop":false,"_isIssue":false,"_isCrime":false}],"_currEventID":7,"_clueTokenValue":0,"_isAlive":true,"_isTurn":false,"_daleyTurnCount":0,"_reasoningValue":3,"_currTile":1,"_tempCurrTile":0,"_currActPoint":100,"_currTrunPoint":0,"_currHP":20,"_MaxHP":20,"_atkPoint":2,"_WishIcon":{"_currTile":0,"_isAlive":false,"_isTurn":false},"_HamIcon":{"_currTile":0,"_isAlive":false,"_isTurn":false},"_HamSaveData":{"_currRoot":0,"_rootChangeValue":33.0,"_nextRootTile":0,"_currRootValue":0,"_currList":[],"_jeonMoveTileListA":[3,1,2,5],"_jeonMoveTileListB":[3,7,5],"_jeonMoveTileListC":[7,9,7,5]},"_JeonIcon":{"_currTile":0,"_isAlive":false,"_isTurn":false},"_JeonSaveData":{"_currRoot":0,"_rootChangeValue":50.0,"_nextRootTile":0,"_currRootValue":0,"_currList":[],"_jeonMoveTileListA":[5,1,0,2,6,10,11,12],"_jeonMoveTileListB":[12,10,7,8,4,0,3,1,5],"_jeonMoveTileListC":[7,0,2,0,4,9,11,13,5],"_jeonMoveTileListD":[11,8,4,0,1,2,8,11,12]},"_YoungIcon":{"_currTile":0,"_isAlive":false,"_isTurn":false},"_YoungSaveData":{"_nextRootTile":0,"_currRootValue":0,"_YoungMoveTileList":[7,8,9,10,11,12,13,12,11,10,9,8,7,6,5,4,6]}},{"isSaveData":false,"SaveDay":"","_currItemDatasList":[],"_currEquipDatasList":[],"_currAidDatasList":[],"_useItemList":[],"_tileMapList":[{"_tileIndex":0,"_SafetyValue":0.0,"_isSafetyEff":false,"_isBlockade":false,"_isIssueIcon":false,"_isShop":false,"_isSpShop":false,"_isIssue":false,"_isCrime":false},{"_tileIndex":0,"_SafetyValue":0.0,"_isSafetyEff":false,"_isBlockade":false,"_isIssueIcon":false,"_isShop":false,"_isSpShop":false,"_isIssue":false,"_isCrime":false},{"_tileIndex":0,"_SafetyValue":0.0,"_isSafetyEff":false,"_isBlockade":false,"_isIssueIcon":false,"_isShop":false,"_isSpShop":false,"_isIssue":false,"_isCrime":false},{"_tileIndex":0,"_SafetyValue":0.0,"_isSafetyEff":false,"_isBlockade":false,"_isIssueIcon":false,"_isShop":false,"_isSpShop":false,"_isIssue":false,"_isCrime":false},{"_tileIndex":0,"_SafetyValue":0.0,"_isSafetyEff":false,"_isBlockade":false,"_isIssueIcon":false,"_isShop":false,"_isSpShop":false,"_isIssue":false,"_isCrime":false},{"_tileIndex":0,"_SafetyValue":0.0,"_isSafetyEff":false,"_isBlockade":false,"_isIssueIcon":false,"_isShop":false,"_isSpShop":false,"_isIssue":false,"_isCrime":false},{"_tileIndex":0,"_SafetyValue":0.0,"_isSafetyEff":false,"_isBlockade":false,"_isIssueIcon":false,"_isShop":false,"_isSpShop":false,"_isIssue":false,"_isCrime":false},{"_tileIndex":0,"_SafetyValue":0.0,"_isSafetyEff":false,"_isBlockade":false,"_isIssueIcon":false,"_isShop":false,"_isSpShop":false,"_isIssue":false,"_isCrime":false},{"_tileIndex":0,"_SafetyValue":0.0,"_isSafetyEff":false,"_isBlockade":false,"_isIssueIcon":false,"_isShop":false,"_isSpShop":false,"_isIssue":false,"_isCrime":false},{"_tileIndex":0,"_SafetyValue":0.0,"_isSafetyEff":false,"_isBlockade":false,"_isIssueIcon":false,"_isShop":false,"_isSpShop":false,"_isIssue":false,"_isCrime":false},{"_tileIndex":0,"_SafetyValue":0.0,"_isSafetyEff":false,"_isBlockade":false,"_isIssueIcon":false,"_isShop":false,"_isSpShop":false,"_isIssue":false,"_isCrime":false},{"_tileIndex":0,"_SafetyValue":0.0,"_isSafetyEff":false,"_isBlockade":false,"_isIssueIcon":false,"_isShop":false,"_isSpShop":false,"_isIssue":false,"_isCrime":false},{"_tileIndex":0,"_SafetyValue":0.0,"_isSafetyEff":false,"_isBlockade":false,"_isIssueIcon":false,"_isShop":false,"_isSpShop":false,"_isIssue":false,"_isCrime":false},{"_tileIndex":0,"_SafetyValue":0.0,"_isSafetyEff":false,"_isBlockade":false,"_isIssueIcon":false,"_isShop":false,"_isSpShop":false,"_isIssue":false,"_isCrime":false}],"_currEventID":0,"_clueTokenValue":0,"_isAlive":false,"_isTurn":false,"_daleyTurnCount":0,"_reasoningValue":0,"_currTile":0,"_tempCurrTile":0,"_currActPoint":0,"_currTrunPoint":0,"_currHP":0,"_MaxHP":0,"_atkPoint":0,"_WishIcon":{"_currTile":-1,"_isAlive":false,"_isTurn":false},"_HamIcon":{"_currTile":-1,"_isAlive":false,"_isTurn":false},"_HamSaveData":{"_currRoot":0,"_rootChangeValue":0.0,"_nextRootTile":0,"_currRootValue":0,"_currList":[],"_jeonMoveTileListA":[],"_jeonMoveTileListB":[],"_jeonMoveTileListC":[]},"_JeonIcon":{"_currTile":-1,"_isAlive":false,"_isTurn":false},"_JeonSaveData":{"_currRoot":0,"_rootChangeValue":0.0,"_nextRootTile":0,"_currRootValue":0,"_currList":[],"_jeonMoveTileListA":[],"_jeonMoveTileListB":[],"_jeonMoveTileListC":[],"_jeonMoveTileListD":[]},"_YoungIcon":{"_currTile":-1,"_isAlive":false,"_isTurn":false},"_YoungSaveData":{"_nextRootTile":0,"_currRootValue":0,"_YoungMoveTileList":[]}},{"isSaveData":false,"SaveDay":"","_currItemDatasList":[],"_currEquipDatasList":[],"_currAidDatasList":[],"_useItemList":[],"_tileMapList":[{"_tileIndex":0,"_SafetyValue":0.0,"_isSafetyEff":false,"_isBlockade":false,"_isIssueIcon":false,"_isShop":false,"_isSpShop":false,"_isIssue":false,"_isCrime":false},{"_tileIndex":0,"_SafetyValue":0.0,"_isSafetyEff":false,"_isBlockade":false,"_isIssueIcon":false,"_isShop":false,"_isSpShop":false,"_isIssue":false,"_isCrime":false},{"_tileIndex":0,"_SafetyValue":0.0,"_isSafetyEff":false,"_isBlockade":false,"_isIssueIcon":false,"_isShop":false,"_isSpShop":false,"_isIssue":false,"_isCrime":false},{"_tileIndex":0,"_SafetyValue":0.0,"_isSafetyEff":false,"_isBlockade":false,"_isIssueIcon":false,"_isShop":false,"_isSpShop":false,"_isIssue":false,"_isCrime":false},{"_tileIndex":0,"_SafetyValue":0.0,"_isSafetyEff":false,"_isBlockade":false,"_isIssueIcon":false,"_isShop":false,"_isSpShop":false,"_isIssue":false,"_isCrime":false},{"_tileIndex":0,"_SafetyValue":0.0,"_isSafetyEff":false,"_isBlockade":false,"_isIssueIcon":false,"_isShop":false,"_isSpShop":false,"_isIssue":false,"_isCrime":false},{"_tileIndex":0,"_SafetyValue":0.0,"_isSafetyEff":false,"_isBlockade":false,"_isIssueIcon":false,"_isShop":false,"_isSpShop":false,"_isIssue":false,"_isCrime":false},{"_tileIndex":0,"_SafetyValue":0.0,"_isSafetyEff":false,"_isBlockade":false,"_isIssueIcon":false,"_isShop":false,"_isSpShop":false,"_isIssue":false,"_isCrime":false},{"_tileIndex":0,"_SafetyValue":0.0,"_isSafetyEff":false,"_isBlockade":false,"_isIssueIcon":false,"_isShop":false,"_isSpShop":false,"_isIssue":false,"_isCrime":false},{"_tileIndex":0,"_SafetyValue":0.0,"_isSafetyEff":false,"_isBlockade":false,"_isIssueIcon":false,"_isShop":false,"_isSpShop":false,"_isIssue":false,"_isCrime":false},{"_tileIndex":0,"_SafetyValue":0.0,"_isSafetyEff":false,"_isBlockade":false,"_isIssueIcon":false,"_isShop":false,"_isSpShop":false,"_isIssue":false,"_isCrime":false},{"_tileIndex":0,"_SafetyValue":0.0,"_isSafetyEff":false,"_isBlockade":false,"_isIssueIcon":false,"_isShop":false,"_isSpShop":false,"_isIssue":false,"_isCrime":false},{"_tileIndex":0,"_SafetyValue":0.0,"_isSafetyEff":false,"_isBlockade":false,"_isIssueIcon":false,"_isShop":false,"_isSpShop":false,"_isIssue":false,"_isCrime":false},{"_tileIndex":0,"_SafetyValue":0.0,"_isSafetyEff":false,"_isBlockade":false,"_isIssueIcon":false,"_isShop":false,"_isSpShop":false,"_isIssue":false,"_isCrime":false}],"_currEventID":0,"_clueTokenValue":0,"_isAlive":false,"_isTurn":false,"_daleyTurnCount":0,"_reasoningValue":0,"_currTile":0,"_tempCurrTile":0,"_currActPoint":0,"_currTrunPoint":0,"_currHP":0,"_MaxHP":0,"_atkPoint":0,"_WishIcon":{"_currTile":-1,"_isAlive":false,"_isTurn":false},"_HamIcon":{"_currTile":-1,"_isAlive":false,"_isTurn":false},"_HamSaveData":{"_currRoot":0,"_rootChangeValue":0.0,"_nextRootTile":0,"_currRootValue":0,"_currList":[],"_jeonMoveTileListA":[],"_jeonMoveTileListB":[],"_jeonMoveTileListC":[]},"_JeonIcon":{"_currTile":-1,"_isAlive":false,"_isTurn":false},"_JeonSaveData":{"_currRoot":0,"_rootChangeValue":0.0,"_nextRootTile":0,"_currRootValue":0,"_currList":[],"_jeonMoveTileListA":[],"_jeonMoveTileListB":[],"_jeonMoveTileListC":[],"_jeonMoveTileListD":[]},"_YoungIcon":{"_currTile":-1,"_isAlive":false,"_isTurn":false},"_YoungSaveData":{"_nextRootTile":0,"_currRootValue":0,"_YoungMoveTileList":[]}}]